rtl/core/riscv_fetch.sv
module riscv_fetch (
    input  logic        clk,      // The heartbeat of the chip
    input  logic        rst_n,    // Reset (Active Low)
    output logic [31:0] pc_out    // The "Address" of the instruction
);

    logic [31:0] pc_reg;

    // This block tells the PC to increment by 4 every clock cycle
    always_ff @(posedge clk or negedge rst_n) begin
        if (!rst_n) begin
            pc_reg <= 32'h0000_0000; // Start at address 0
        end else begin
            pc_reg <= pc_reg + 4;    // Move to next instruction
        end
    end

    assign pc_out = pc_reg;

endmodule

tb/tb_riscv_fetch.sv
`timescale 1ns/1ps

module tb_riscv_fetch;

    // 1. Signals to connect to the module
    logic        clk;
    logic        rst_n;
    logic [31:0] pc_out;

    // 2. Instantiate the module (Connect the wires)
    riscv_fetch dut (
        .clk(clk),
        .rst_n(rst_n),
        .pc_out(pc_out)
    );

    // 3. Generate the Clock (The heartbeat)
    // This creates a 100MHz clock (10ns period)
    always #5 clk = ~clk;

    // 4. The Test Sequence
    initial begin
        // Initialize signals
        clk = 0;
        rst_n = 0;   // Start in Reset

        // Wait 20ns, then release Reset
        #20 rst_n = 1;

        // Let it run for 100ns to see the PC increment
        #100;

        $display("Test Complete. Final PC: %h", pc_out);
        $finish;     // Stop the simulation
    end

    // 5. Waveform Dump (For GTKWave)
    initial begin
        $dumpfile("waveform.vcd");
        $dumpvars(0, tb_riscv_fetch);
    end

endmodule

waveform.vcd
$date
	Wed Mar 18 15:27:44 2026
$end
$version
	Icarus Verilog
$end
$timescale
	1ps
$end
$scope module tb_riscv_fetch $end
$var wire 32 ! pc_out [31:0] $end
$var reg 1 " clk $end
$var reg 1 # rst_n $end
$scope module dut $end
$var wire 1 " clk $end
$var wire 32 $ pc_out [31:0] $end
$var wire 1 # rst_n $end
$var reg 32 % pc_reg [31:0] $end
$upscope $end
$upscope $end
$enddefinitions $end
$comment Show the parameter values. $end
$dumpall
$end
#0
$dumpvars
b0 %
b0 $
0#
0"
b0 !
$end
#5000
1"
#10000
0"
#15000
1"
#20000
0"
1#
#25000
b100 !
b100 $
b100 %
1"
#30000
0"
#35000
b1000 !
b1000 $
b1000 %
1"
#40000
0"
#45000
b1100 !
b1100 $
b1100 %
1"
#50000
0"
#55000
b10000 !
b10000 $
b10000 %
1"
#60000
0"
#65000
b10100 !
b10100 $
b10100 %
1"
#70000
0"
#75000
b11000 !
b11000 $
b11000 %
1"
#80000
0"
#85000
b11100 !
b11100 $
b11100 %
1"
#90000
0"
#95000
b100000 !
b100000 $
b100000 %
1"
#100000
0"
#105000
b100100 !
b100100 $
b100100 %
1"
#110000
0"
#115000
b101000 !
b101000 $
b101000 %
1"
